poly_match_rs-0.1.5.dist-info/METADATA
poly_match_rs-0.1.5.dist-info/WHEEL
poly_match_rs-0.1.5.dist-info/entry_points.txt
poly_match_rs/v2.py
poly_match_rs/v1.py
poly_match_rs/v0.py
poly_match_rs/__main__.py
poly_match_rs/__init__.py
poly_match_rs/baseline.py
poly_match_rs/core.cpython-310-x86_64-linux-gnu.so
poly_match_rs-0.1.5.dist-info/RECORD
