Metadata-Version: 2.3
Name: poly-match-rs
Version: 0.1.5
Classifier: Programming Language :: Rust
Classifier: Programming Language :: Python :: Implementation :: CPython
Classifier: Programming Language :: Python :: Implementation :: PyPy
Requires-Dist: jsonargparse >=4.32.1
Requires-Dist: rich >=13.8.1
Requires-Dist: numpy >=1.24.4
Requires-Dist: pytest ; extra == 'tests'
Provides-Extra: tests
Requires-Python: >=3.8
